azure/mgmt/healthcareapis/__init__.py
azure/mgmt/healthcareapis/_configuration.py
azure/mgmt/healthcareapis/_healthcare_apis_management_client.py
azure/mgmt/healthcareapis/_patch.py
azure/mgmt/healthcareapis/_serialization.py
azure/mgmt/healthcareapis/_vendor.py
azure/mgmt/healthcareapis/_version.py
azure/mgmt/healthcareapis/py.typed
azure/mgmt/healthcareapis/aio/__init__.py
azure/mgmt/healthcareapis/aio/_configuration.py
azure/mgmt/healthcareapis/aio/_healthcare_apis_management_client.py
azure/mgmt/healthcareapis/aio/_patch.py
azure/mgmt/healthcareapis/aio/operations/__init__.py
azure/mgmt/healthcareapis/aio/operations/_dicom_services_operations.py
azure/mgmt/healthcareapis/aio/operations/_fhir_destinations_operations.py
azure/mgmt/healthcareapis/aio/operations/_fhir_services_operations.py
azure/mgmt/healthcareapis/aio/operations/_iot_connector_fhir_destination_operations.py
azure/mgmt/healthcareapis/aio/operations/_iot_connectors_operations.py
azure/mgmt/healthcareapis/aio/operations/_operation_results_operations.py
azure/mgmt/healthcareapis/aio/operations/_operations.py
azure/mgmt/healthcareapis/aio/operations/_patch.py
azure/mgmt/healthcareapis/aio/operations/_private_endpoint_connections_operations.py
azure/mgmt/healthcareapis/aio/operations/_private_link_resources_operations.py
azure/mgmt/healthcareapis/aio/operations/_services_operations.py
azure/mgmt/healthcareapis/aio/operations/_workspace_private_endpoint_connections_operations.py
azure/mgmt/healthcareapis/aio/operations/_workspace_private_link_resources_operations.py
azure/mgmt/healthcareapis/aio/operations/_workspaces_operations.py
azure/mgmt/healthcareapis/models/__init__.py
azure/mgmt/healthcareapis/models/_healthcare_apis_management_client_enums.py
azure/mgmt/healthcareapis/models/_models_py3.py
azure/mgmt/healthcareapis/models/_patch.py
azure/mgmt/healthcareapis/operations/__init__.py
azure/mgmt/healthcareapis/operations/_dicom_services_operations.py
azure_mgmt_healthcareapis-2.1.0.dist-info/LICENSE
azure_mgmt_healthcareapis-2.1.0.dist-info/METADATA
azure_mgmt_healthcareapis-2.1.0.dist-info/WHEEL
azure_mgmt_healthcareapis-2.1.0.dist-info/top_level.txt
azure_mgmt_healthcareapis-2.1.0.dist-info/RECORD
